{"id":"91768331-1f8a-4b29-ad46-f0177b094f3f","timestamp":1761926766845,"matcher":{"static":{"/__nuxt_content/landing/sql_dump.txt":{"prerender":true},"/__nuxt_content/docs/sql_dump.txt":{"prerender":true}},"wildcard":{},"dynamic":{}},"prerendered":["/","/getting-started/installation","/getting-started/migration","/essentials/images-embeds","/getting-started/introduction","/getting-started/studio","/getting-started/project-structure","/essentials/code-blocks","/essentials/markdown-syntax","/essentials/components"]}